{
	"files": [

	],
	"folders": {
		"Characters": {
			"files": [
				"character-1639439096.json"
			],
			"folders": {

			},
			"metadata": {
				"color": null,
				"folded": false
			}
		},
		"Definitions": {
			"files": [

			],
			"folders": {

			},
			"metadata": {
				"color": null,
				"folded": false
			}
		},
		"Themes": {
			"files": [
				"default-theme.cfg",
				"theme-1639440383.cfg"
			],
			"folders": {

			},
			"metadata": {
				"color": null,
				"folded": false
			}
		},
		"Timelines": {
			"files": [
				"timeline-1639439133.json"
			],
			"folders": {

			},
			"metadata": {
				"color": null,
				"folded": false
			}
		}
	}
}
